celldiffusion/__init__.py
celldiffusion/diffusion/__init__.py
celldiffusion/diffusion/feature_encoder.py
celldiffusion/diffusion/gnd.py
celldiffusion/diffusion/graph_DIF.py
celldiffusion/sc_analysis/__init__.py
celldiffusion/sc_analysis/annotation.py
celldiffusion/sc_analysis/clustering.py
celldiffusion/sc_analysis/preprocess.py
celldiffusion/sc_analysis/trajectory.py
celldiffusion/sc_analysis/trajectory_plot.py
celldiffusion/sc_graph/__init__.py
celldiffusion/sc_graph/build_graph.py
celldiffusion/sc_graph/graph_attention.py
celldiffusion/sc_graph/graph_modularity.py
celldiffusion/sc_integration/__init__.py
celldiffusion/sc_integration/integration_DIF.py
celldiffusion/sc_integration/integration_graph.py
celldiffusion/utils/__init__.py
celldiffusion/utils/info_log.py
celldiffusion/utils/utility_fn.py
celldiffusion-0.1.2.dist-info/METADATA
celldiffusion-0.1.2.dist-info/WHEEL
celldiffusion-0.1.2.dist-info/top_level.txt
celldiffusion-0.1.2.dist-info/RECORD
