Metadata-Version: 2.1
Name: celldiffusion
Version: 0.1.2
Summary: CellDiffusion(Single-Cell graph neural Diffusion) is a physics-informed graph generative model to do scRNA-seq analysis. CellDiffusion investigates cellular dynamics utilizing an attention-based neural network.
Home-page: https://github.com/CZCBLab/CellDiffusion
Author: Yuchen Liu
Author-email: ycliu137@bu.edu
License: MIT
Keywords: single-cell,diffusion
Platform: UNKNOWN
Classifier: Programming Language :: Python :: 3
Classifier: License :: OSI Approved :: MIT License
Classifier: Operating System :: OS Independent
Requires-Python: >=3.9, <=3.12
Requires-Dist: leidenalg (>=0.8.10)
Requires-Dist: matplotlib (>=3.5.1)
Requires-Dist: networkx (>=2.6.3)
Requires-Dist: numpy (>=1.26.4)
Requires-Dist: pandas (>=1.3.5)
Requires-Dist: python-igraph (>=0.9.9)
Requires-Dist: python-louvain (>=0.16)
Requires-Dist: scanpy
Requires-Dist: scikit-learn (>=1.0.2)
Requires-Dist: scipy (>=1.7.3)
Requires-Dist: torch (>=1.13.1)
Requires-Dist: torchaudio (>=0.13.1)
Requires-Dist: torchvision (>=0.14.1)
Requires-Dist: umap-learn (>=0.5.2)
